LICENSE
README.md
setup.py
matching_experiments/__init__.py
matching_experiments/analyze_exaggeration.py
matching_experiments/domain_and_lexical_analysis.py
matching_experiments/eval_evidence_retrieval.py
matching_experiments/eval_unsupervised_nli.py
matching_experiments/eval_unsupervised_paraphrase_detection.py
matching_experiments/eval_unsupervised_sts.py
matching_experiments/predict_and_rank_tweet_similarity.py
matching_experiments/predict_similarity_scoring_unlabelled.py
matching_experiments/predict_similarity_scoring_unlabelled_sbert.py
matching_experiments/predict_title_tweet_similarity.py
matching_experiments/train_paraphrase_generator.py
matching_experiments/train_supervised.py
matching_experiments/train_supervised_sentence_transformers.py
matching_experiments/utils/__init__.py
matching_experiments/utils/data_processor.py
matching_experiments/utils/metrics.py
matching_experiments/utils/model.py
matching_experiments/utils/rank_metrics.py
matching_experiments/utils/trainer.py
scientific_information_change/__init__.py
scientific_information_change/estimate_similarity.py
scientific_information_change.egg-info/PKG-INFO
scientific_information_change.egg-info/SOURCES.txt
scientific_information_change.egg-info/dependency_links.txt
scientific_information_change.egg-info/requires.txt
scientific_information_change.egg-info/top_level.txt