Metadata-Version: 2.1
Name: scientific-information-change
Version: 1.0.0
Summary: This package is used to estimate the information matching score (IMS) of scientific sentences. IMS is a measure of the similarity of the information contained in scientific findings i.e. how similar are the scientific findings described by two scientific sentences. This can be used to match sentences describing the same scientific findings or measure the degree to which sentences differ in the findings they describe.
Author: Dustin Wright
Author-email: dw@di.ku.dk
Requires-Python: >=3.6
License-File: LICENSE
